{"extraResources":{"example.01.mu":"TVXzASFjMTs3IDgNCjEgNSA2IDEgMSAyIDMNCg=="},"scoring":null,"notes":"The subarray {$6, 1, 1$} has a maximum subarray sum less than or equal $8$.","legend":"You are given an array $a$ of $n$ positive integers and integer $m$.\n\nAnd you asked to find the maximum subarray sum less than or equal to $m$.\n\n$Note: $ empty subarray has sum equals $0$.","authorLogin":"mazen_ghanayem","language":"english","timeLimit":1000,"output":"Output the maximum subarray sum less than or equal to $m$.","inputFile":"stdin","outputFile":"stdout","input":"First line contains $n$, $m$ -- $(1\\le n\\le 10^5)$ , $(1\\le m\\le 10^9)$-- number of array elements and target sum.\n\nSecond line contains $n$ integers $a_1,\\cdots,a_n$ --$(1 \\le a_i \\le 10^9)$.","authorName":"Mazen Ghanayem","sampleTests":[{"output":"8\n","input":"7 8\n1 5 6 1 1 2 3\n","inputFile":"example.01","outputFile":"example.01.a"}],"name":"Subarray Sum","interaction":null,"memoryLimit":268435456,"tutorial":""}
